esp_rfc2217_server/__init__.py
esp_rfc2217_server/__main__.py
esp_rfc2217_server/esp_port_manager.py
esp_rfc2217_server/redirector.py
espefuse/__init__.py
espefuse/__main__.py
espefuse/efuse/__init__.py
espefuse/efuse/base_fields.py
espefuse/efuse/base_operations.py
espefuse/efuse/csv_table_parser.py
espefuse/efuse/emulate_efuse_controller_base.py
espefuse/efuse/mem_definition_base.py
espefuse/efuse/util.py
espefuse/efuse/esp32/__init__.py
espefuse/efuse/esp32/emulate_efuse_controller.py
espefuse/efuse/esp32/fields.py
espefuse/efuse/esp32/mem_definition.py
espefuse/efuse/esp32/operations.py
espefuse/efuse/esp32c2/__init__.py
espefuse/efuse/esp32c2/emulate_efuse_controller.py
espefuse/efuse/esp32c2/fields.py
espefuse/efuse/esp32c2/mem_definition.py
espefuse/efuse/esp32c2/operations.py
espefuse/efuse/esp32c3/__init__.py
espefuse/efuse/esp32c3/emulate_efuse_controller.py
espefuse/efuse/esp32c3/fields.py
espefuse/efuse/esp32c3/mem_definition.py
espefuse/efuse/esp32c3/operations.py
espefuse/efuse/esp32c5/__init__.py
espefuse/efuse/esp32c5/emulate_efuse_controller.py
espefuse/efuse/esp32c5/fields.py
espefuse/efuse/esp32c5/mem_definition.py
espefuse/efuse/esp32c5/operations.py
espefuse/efuse/esp32c5beta3/__init__.py
espefuse/efuse/esp32c5beta3/emulate_efuse_controller.py
espefuse/efuse/esp32c5beta3/fields.py
espefuse/efuse/esp32c5beta3/mem_definition.py
espefuse/efuse/esp32c5beta3/operations.py
espefuse/efuse/esp32c6/__init__.py
espefuse/efuse/esp32c6/emulate_efuse_controller.py
espefuse/efuse/esp32c6/fields.py
espefuse/efuse/esp32c6/mem_definition.py
espefuse/efuse/esp32c6/operations.py
espefuse/efuse/esp32c61/__init__.py
espefuse/efuse/esp32c61/emulate_efuse_controller.py
espefuse/efuse/esp32c61/fields.py
espefuse/efuse/esp32c61/mem_definition.py
espefuse/efuse/esp32c61/operations.py
espefuse/efuse/esp32h2/__init__.py
espefuse/efuse/esp32h2/emulate_efuse_controller.py
espefuse/efuse/esp32h2/fields.py
espefuse/efuse/esp32h2/mem_definition.py
esptool-4.8.0.dist-info/LICENSE
esptool-4.8.0.dist-info/METADATA
esptool-4.8.0.dist-info/WHEEL
esptool-4.8.0.dist-info/top_level.txt
esptool-4.8.0.dist-info/RECORD
