Metadata-Version: 2.1
Name: esptool
Version: 4.8.0
Summary: A serial utility to communicate & flash code to Espressif chips.
Author: Fredrik Ahlberg (themadinventor), Angus Gratton (projectgus), Espressif Systems
License: GPLv2+
Project-URL: Homepage, https://github.com/espressif/esptool/
Project-URL: Documentation, https://docs.espressif.com/projects/esptool/
Project-URL: Source, https://github.com/espressif/esptool/
Project-URL: Tracker, https://github.com/espressif/esptool/issues/
Project-URL: Changelog, https://github.com/espressif/esptool/blob/master/CHANGELOG.md
Classifier: Development Status :: 5 - Production/Stable
Classifier: Intended Audience :: Developers
Classifier: Natural Language :: English
Classifier: Operating System :: POSIX
Classifier: Operating System :: Microsoft :: Windows
Classifier: Operating System :: MacOS :: MacOS X
Classifier: Topic :: Software Development :: Embedded Systems
Classifier: Environment :: Console
Classifier: License :: OSI Approved :: GNU General Public License v2 or later (GPLv2+)
Classifier: Programming Language :: Python :: 3.7
Classifier: Programming Language :: Python :: 3.8
Classifier: Programming Language :: Python :: 3.9
Classifier: Programming Language :: Python :: 3.10
Classifier: Programming Language :: Python :: 3.11
Classifier: Programming Language :: Python :: 3.12
Requires-Python: >=3.7
Provides-Extra: dev
Provides-Extra: hsm
License-File: LICENSE
